pycggtts/__init__.py
pycggtts/cggtts.py
pycggtts/code.py
pycggtts/delay.py
pycggtts/reftime.py
pycggtts/track/__init__.py
pycggtts/track/track.py
pycggtts/version.py
pycggtts-0.1.2.dist-info/LICENSE
pycggtts-0.1.2.dist-info/METADATA
pycggtts-0.1.2.dist-info/WHEEL
pycggtts-0.1.2.dist-info/RECORD
