Metadata-Version: 2.1
Name: pycggtts
Version: 0.1.2
Summary: Remote clock comparison using CGGTTS in Python
License: LGPLv3
Author: Víctor Vázquez
Author-email: victorvazrod@gmail.com
Requires-Python: >=3.11,<4.0
Classifier: License :: Other/Proprietary License
Classifier: Programming Language :: Python :: 3
Classifier: Programming Language :: Python :: 3.11
Classifier: Programming Language :: Python :: 3.12
Classifier: Programming Language :: Python :: 3.13
Requires-Dist: hifitime (>=4.0.0,<5.0.0)
Requires-Dist: numpy (>=2.1.2,<3.0.0)
